dowright/__init__.py
dowright/__main__.py
dowright/ansible_expand_hosts.py
dowright/build.py
dowright/inventory.py
dowright/spec.py
dowright/yaml.py
dowright-0.0.0a7.dist-info/DESCRIPTION.rst
dowright-0.0.0a7.dist-info/METADATA
dowright-0.0.0a7.dist-info/RECORD
dowright-0.0.0a7.dist-info/WHEEL
dowright-0.0.0a7.dist-info/metadata.json
dowright-0.0.0a7.dist-info/top_level.txt
