Metadata-Version: 2.0
Name: dowright
Version: 0.0.0a7
Summary: Simple YAML-based specification for creation and configuration of DigitalOcean droplets
Home-page: https://bitbucket.org/dogwynn/dowright
Author: David O'Gwynn
Author-email: dogywnn@acm.org
License: MIT
Keywords: digitalocean yaml specification ansible development helper utility
Platform: UNKNOWN
Classifier: Development Status :: 3 - Alpha
Classifier: Intended Audience :: Developers
Classifier: License :: OSI Approved :: BSD License
Classifier: Programming Language :: Python :: 3
Requires-Dist: ruamel.yaml
Requires-Dist: paramiko
Requires-Dist: python-digitalocean
Requires-Dist: memoized-property
Requires-Dist: gems
Requires-Dist: tokenmanager
Requires-Dist: jinja2
